ncvue/__init__.py
ncvue/__main__.py
ncvue/_version.py
ncvue/ncvcontour.py
ncvue/ncvmain.py
ncvue/ncvmap.py
ncvue/ncvmethods.py
ncvue/ncvscatter.py
ncvue/ncvscreen.py
ncvue/ncvue.py
ncvue/ncvutils.py
ncvue/ncvwidgets.py
ncvue/tooltip.py
ncvue/images/Accent.png
ncvue/images/Blues.png
ncvue/images/BrBG.png
ncvue/images/BuGn.png
ncvue/images/BuPu.png
ncvue/images/CMRmap.png
ncvue/images/Dark2.png
ncvue/images/GnBu.png
ncvue/images/Grays.png
ncvue/images/Greens.png
ncvue/images/Greys.png
ncvue/images/OrRd.png
ncvue/images/Oranges.png
ncvue/images/PRGn.png
ncvue/images/Paired.png
ncvue/images/Pastel1.png
ncvue/images/Pastel2.png
ncvue/images/PiYG.png
ncvue/images/PuBu.png
ncvue/images/PuBuGn.png
ncvue/images/PuOr.png
ncvue/images/PuRd.png
ncvue/images/Purples.png
ncvue/images/RdBu.png
ncvue/images/RdGy.png
ncvue/images/RdPu.png
ncvue/images/RdYlBu.png
ncvue/images/RdYlGn.png
ncvue/images/Reds.png
ncvue/images/Set1.png
ncvue/images/Set2.png
ncvue/images/Set3.png
ncvue/images/Spectral.png
ncvue/images/Wistia.png
ncvue/images/YlGn.png
ncvue/images/YlGnBu.png
ncvue/images/YlOrBr.png
ncvue/images/YlOrRd.png
ncvue/images/afmhot.png
ncvue/images/autumn.png
ncvue/images/berlin.png
ncvue/images/binary.png
ncvue/images/bone.png
ncvue/images/brg.png
ncvue/images/bwr.png
ncvue/images/cividis.png
ncvue/images/cool.png
ncvue/images/coolwarm.png
ncvue/images/copper.png
ncvue/images/cubehelix.png
ncvue/images/flag.png
ncvue/images/gist_earth.png
ncvue/images/gist_gray.png
ncvue/images/gist_grey.png
ncvue/images/gist_heat.png
ncvue/images/gist_ncar.png
ncvue/images/gist_rainbow.png
ncvue/images/gist_stern.png
ncvue/images/gist_yarg.png
ncvue/images/gist_yerg.png
ncvue/images/gnuplot.png
ncvue/images/gnuplot2.png
ncvue/images/gray.png
ncvue/images/grey.png
ncvue/images/hot.png
ncvue/images/hsv.png
ncvue/images/inferno.png
ncvue/images/jet.png
ncvue/images/magma.png
ncvue/images/managua.png
ncvue/images/ncvue_icon.png
ncvue/images/nipy_spectral.png
ncvue/images/ocean.png
ncvue-6.4.1.dist-info/licenses/AUTHORS.rst
ncvue-6.4.1.dist-info/licenses/LICENSE
ncvue-6.4.1.dist-info/METADATA
ncvue-6.4.1.dist-info/WHEEL
ncvue-6.4.1.dist-info/entry_points.txt
ncvue-6.4.1.dist-info/top_level.txt
ncvue-6.4.1.dist-info/RECORD
