Metadata-Version: 2.4
Name: ncvue
Version: 6.4.1
Summary: ncvue: A minimal GUI for a quick view of netcdf files, aiming to be a drop-in replacement for ncview and panoply
Home-page: https://github.com/mcuntz/ncvue
Author: Matthias Cuntz
Author-email: mc@macu.de
Maintainer: Matthias Cuntz
Maintainer-email: mc@macu.de
License: MIT
Project-URL: Documentation, https://mcuntz.github.io/ncvue/
Project-URL: Source, https://github.com/mcuntz/ncvue
Project-URL: Tracker, https://github.com/mcuntz/ncvue/issues
Project-URL: Changelog, https://github.com/mcuntz/ncvue/blob/main/CHANGELOG.rst
Platform: any
Classifier: Development Status :: 5 - Production/Stable
Classifier: Intended Audience :: Developers
Classifier: Intended Audience :: End Users/Desktop
Classifier: Intended Audience :: Science/Research
Classifier: Natural Language :: English
Classifier: Operating System :: MacOS
Classifier: Operating System :: MacOS :: MacOS X
Classifier: Operating System :: Microsoft
Classifier: Operating System :: Microsoft :: Windows
Classifier: Operating System :: POSIX
Classifier: Operating System :: Unix
Classifier: Programming Language :: Python
Classifier: Programming Language :: Python :: 3
Classifier: Programming Language :: Python :: 3 :: Only
Classifier: Programming Language :: Python :: 3.8
Classifier: Programming Language :: Python :: 3.9
Classifier: Programming Language :: Python :: 3.10
Classifier: Programming Language :: Python :: 3.11
Classifier: Programming Language :: Python :: 3.12
Classifier: Programming Language :: Python :: 3.13
Classifier: Topic :: Scientific/Engineering
Classifier: Topic :: Scientific/Engineering :: Atmospheric Science
Classifier: Topic :: Scientific/Engineering :: Hydrology
Classifier: Topic :: Scientific/Engineering :: Mathematics
Classifier: Topic :: Software Development
Classifier: Topic :: Utilities
Requires-Python: >=3.8
License-File: LICENSE
License-File: AUTHORS.rst
Requires-Dist: numpy
Requires-Dist: scipy
Requires-Dist: cftime
Requires-Dist: netcdf4
Requires-Dist: cython
Requires-Dist: pyshp
Requires-Dist: six
Requires-Dist: shapely
Requires-Dist: matplotlib
Requires-Dist: pykdtree
Requires-Dist: cartopy
Provides-Extra: doc
Requires-Dist: numpy; extra == "doc"
Requires-Dist: scipy; extra == "doc"
Requires-Dist: cftime; extra == "doc"
Requires-Dist: netcdf4; extra == "doc"
Requires-Dist: pyproj; extra == "doc"
Requires-Dist: geos; extra == "doc"
Requires-Dist: cython; extra == "doc"
Requires-Dist: pyshp; extra == "doc"
Requires-Dist: six; extra == "doc"
Requires-Dist: shapely; extra == "doc"
Requires-Dist: pillow; extra == "doc"
Requires-Dist: pykdtree; extra == "doc"
Requires-Dist: matplotlib; extra == "doc"
Requires-Dist: numpydoc<2,>=1.1; extra == "doc"
Requires-Dist: sphinx>=3; extra == "doc"
Requires-Dist: sphinx_book_theme>=1.0.1; extra == "doc"
Provides-Extra: test
Requires-Dist: numpy; extra == "test"
Requires-Dist: coverage[toml]>=5.2.1; extra == "test"
Requires-Dist: pytest>=6.0; extra == "test"
Requires-Dist: pytest-cov>=2.11.0; extra == "test"
Dynamic: license-file
